125softNLP/__init__.py
125softNLP/test.py
125softNLP/bert/__init__.py
125softNLP/bert/args.py
125softNLP/bert/extract_feature.py
125softNLP/bert/graph.py
125softNLP/bert/modeling.py
125softNLP/bert/optimization.py
125softNLP/bert/tokenization.py
125softNLP/classification/__init__.py
125softNLP/classification/bert_dnn.py
125softNLP/classification/extract_feature.py
125softNLP/classification/load_data.py
125softNLP/classification/model_predict.py
125softNLP/classification/model_train.py
125softNLP/classification/pre.py
125softNLP/clean/__init__.py
125softNLP/enhancement/__init__.py
125softNLP/enhancement/augment.py
125softNLP/enhancement/ciLin.py
125softNLP/enhancement/eda.py
125softNLP/enhancement/transform.py
125softNLP/enhancement/translate.py
125softNLP/extraction/__init__.py
125softNLP/extraction/keyword.py
125softNLP/kashgari/__init__.py
125softNLP/kashgari/__version__.py
125softNLP/kashgari/callbacks.py
125softNLP/kashgari/corpus.py
125softNLP/kashgari/macros.py
125softNLP/kashgari/migeration.py
125softNLP/kashgari/migration.py
125softNLP/kashgari/utils.py
125softNLP/kashgari/version.py
125softNLP/kashgari/embeddings/__init__.py
125softNLP/kashgari/embeddings/bare_embedding.py
125softNLP/kashgari/embeddings/base_embedding.py
125softNLP/kashgari/embeddings/bert_embedding.py
125softNLP/kashgari/embeddings/bert_embedding_v2.py
125softNLP/kashgari/embeddings/gpt_2_embedding.py
125softNLP/kashgari/embeddings/numeric_feature_embedding.py
125softNLP/kashgari/embeddings/stacked_embedding.py
125softNLP/kashgari/embeddings/word_embedding.py
125softNLP/kashgari/layers/__init__.py
125softNLP/kashgari/layers/att_wgt_avg_layer.py
125softNLP/kashgari/layers/crf.py
125softNLP/kashgari/layers/kmax_pool_layer.py
125softNLP/kashgari/layers/non_masking_layer.py
125softNLP/kashgari/processors/__init__.py
125softNLP/kashgari/processors/base_processor.py
125softNLP/kashgari/processors/classification_processor.py
125softNLP/kashgari/processors/labeling_processor.py
125softNLP-0.0.1.dist-info/LICENSE
125softNLP-0.0.1.dist-info/METADATA
125softNLP-0.0.1.dist-info/WHEEL
125softNLP-0.0.1.dist-info/top_level.txt
125softNLP-0.0.1.dist-info/RECORD
