Metadata-Version: 2.1
Name: 125softNLP
Version: 0.0.1
Summary: Python wrapper for pysoftNLP: Natural language processing project of 863 Software Incubator Co., Ltd
Home-page: https://github.com/pypa/sampleproject
Author: lvweijia
Author-email: 1936094276@qq.com
License: UNKNOWN
Platform: UNKNOWN
Classifier: Programming Language :: Python :: 3
Classifier: License :: OSI Approved :: MIT License
Classifier: Operating System :: OS Independent
Requires-Dist: tensorflow
